easy_middleware/__init__.py
easy_middleware/correlation.py
easy_middleware/logger.py
easy_middleware/security.py
easy_middleware/timing.py
easy_middleware-0.1.1.dist-info/licenses/LICENSE
easy_middleware-0.1.1.dist-info/METADATA
easy_middleware-0.1.1.dist-info/WHEEL
easy_middleware-0.1.1.dist-info/top_level.txt
easy_middleware-0.1.1.dist-info/RECORD
